{"trial_id": "37", "hyperparameters": {"space": [{"class_name": "Choice", "config": {"name": "learning_rate", "default": 0.001, "conditions": [], "values": [0.001, 0.01, 0.1], "ordered": true}}, {"class_name": "Int", "config": {"name": "layers_units_x", "default": null, "conditions": [], "min_value": 5, "max_value": 50, "step": 1, "sampling": "linear"}}, {"class_name": "Int", "config": {"name": "layers_", "default": null, "conditions": [], "min_value": 1, "max_value": 30, "step": 1, "sampling": "linear"}}, {"class_name": "Choice", "config": {"name": "dp_rate_0", "default": 0.25, "conditions": [], "values": [0.25, 0.5, 0.75], "ordered": true}}, {"class_name": "Int", "config": {"name": "units_0", "default": null, "conditions": [], "min_value": 5, "max_value": 100, "step": 5, "sampling": "linear"}}, {"class_name": "Choice", "config": {"name": "dp_rate_1", "default": 0.25, "conditions": [], "values": [0.25, 0.5, 0.75], "ordered": true}}, {"class_name": "Int", "config": {"name": "units_1", "default": null, "conditions": [], "min_value": 5, "max_value": 100, "step": 5, "sampling": "linear"}}, {"class_name": "Choice", "config": {"name": "dp_rate_2", "default": 0.25, "conditions": [], "values": [0.25, 0.5, 0.75], "ordered": true}}, {"class_name": "Int", "config": {"name": "units_2", "default": null, "conditions": [], "min_value": 5, "max_value": 100, "step": 5, "sampling": "linear"}}, {"class_name": "Choice", "config": {"name": "dp_rate_3", "default": 0.25, "conditions": [], "values": [0.25, 0.5, 0.75], "ordered": true}}, {"class_name": "Int", "config": {"name": "units_3", "default": null, "conditions": [], "min_value": 5, "max_value": 100, "step": 5, "sampling": "linear"}}, {"class_name": "Choice", "config": {"name": "dp_rate_4", "default": 0.25, "conditions": [], "values": [0.25, 0.5, 0.75], "ordered": true}}, {"class_name": "Int", "config": {"name": "units_4", "default": null, "conditions": [], "min_value": 5, "max_value": 100, "step": 5, "sampling": "linear"}}, {"class_name": "Choice", "config": {"name": "dp_rate_5", "default": 0.25, "conditions": [], "values": [0.25, 0.5, 0.75], "ordered": true}}, {"class_name": "Int", "config": {"name": "units_5", "default": null, "conditions": [], "min_value": 5, "max_value": 100, "step": 5, "sampling": "linear"}}, {"class_name": "Choice", "config": {"name": "dp_rate_6", "default": 0.25, "conditions": [], "values": [0.25, 0.5, 0.75], "ordered": true}}, {"class_name": "Int", "config": {"name": "units_6", "default": null, "conditions": [], "min_value": 5, "max_value": 100, "step": 5, "sampling": "linear"}}, {"class_name": "Choice", "config": {"name": "dp_rate_7", "default": 0.25, "conditions": [], "values": [0.25, 0.5, 0.75], "ordered": true}}, {"class_name": "Int", "config": {"name": "units_7", "default": null, "conditions": [], "min_value": 5, "max_value": 100, "step": 5, "sampling": "linear"}}, {"class_name": "Choice", "config": {"name": "dp_rate_8", "default": 0.25, "conditions": [], "values": [0.25, 0.5, 0.75], "ordered": true}}, {"class_name": "Int", "config": {"name": "units_8", "default": null, "conditions": [], "min_value": 5, "max_value": 100, "step": 5, "sampling": "linear"}}, {"class_name": "Choice", "config": {"name": "dp_rate_9", "default": 0.25, "conditions": [], "values": [0.25, 0.5, 0.75], "ordered": true}}, {"class_name": "Int", "config": {"name": "units_9", "default": null, "conditions": [], "min_value": 5, "max_value": 100, "step": 5, "sampling": "linear"}}, {"class_name": "Choice", "config": {"name": "dp_rate_10", "default": 0.25, "conditions": [], "values": [0.25, 0.5, 0.75], "ordered": true}}, {"class_name": "Int", "config": {"name": "units_10", "default": null, "conditions": [], "min_value": 5, "max_value": 100, "step": 5, "sampling": "linear"}}, {"class_name": "Choice", "config": {"name": "dp_rate_11", "default": 0.25, "conditions": [], "values": [0.25, 0.5, 0.75], "ordered": true}}, {"class_name": "Int", "config": {"name": "units_11", "default": null, "conditions": [], "min_value": 5, "max_value": 100, "step": 5, "sampling": "linear"}}, {"class_name": "Choice", "config": {"name": "dp_rate_12", "default": 0.25, "conditions": [], "values": [0.25, 0.5, 0.75], "ordered": true}}, {"class_name": "Int", "config": {"name": "units_12", "default": null, "conditions": [], "min_value": 5, "max_value": 100, "step": 5, "sampling": "linear"}}, {"class_name": "Choice", "config": {"name": "dp_rate_13", "default": 0.25, "conditions": [], "values": [0.25, 0.5, 0.75], "ordered": true}}, {"class_name": "Int", "config": {"name": "units_13", "default": null, "conditions": [], "min_value": 5, "max_value": 100, "step": 5, "sampling": "linear"}}, {"class_name": "Choice", "config": {"name": "dp_rate_14", "default": 0.25, "conditions": [], "values": [0.25, 0.5, 0.75], "ordered": true}}, {"class_name": "Int", "config": {"name": "units_14", "default": null, "conditions": [], "min_value": 5, "max_value": 100, "step": 5, "sampling": "linear"}}, {"class_name": "Choice", "config": {"name": "dp_rate_15", "default": 0.25, "conditions": [], "values": [0.25, 0.5, 0.75], "ordered": true}}, {"class_name": "Int", "config": {"name": "units_15", "default": null, "conditions": [], "min_value": 5, "max_value": 100, "step": 5, "sampling": "linear"}}, {"class_name": "Choice", "config": {"name": "dp_rate_16", "default": 0.25, "conditions": [], "values": [0.25, 0.5, 0.75], "ordered": true}}, {"class_name": "Int", "config": {"name": "units_16", "default": null, "conditions": [], "min_value": 5, "max_value": 100, "step": 5, "sampling": "linear"}}, {"class_name": "Choice", "config": {"name": "dp_rate_17", "default": 0.25, "conditions": [], "values": [0.25, 0.5, 0.75], "ordered": true}}, {"class_name": "Int", "config": {"name": "units_17", "default": null, "conditions": [], "min_value": 5, "max_value": 100, "step": 5, "sampling": "linear"}}, {"class_name": "Choice", "config": {"name": "dp_rate_18", "default": 0.25, "conditions": [], "values": [0.25, 0.5, 0.75], "ordered": true}}, {"class_name": "Int", "config": {"name": "units_18", "default": null, "conditions": [], "min_value": 5, "max_value": 100, "step": 5, "sampling": "linear"}}, {"class_name": "Choice", "config": {"name": "dp_rate_19", "default": 0.25, "conditions": [], "values": [0.25, 0.5, 0.75], "ordered": true}}, {"class_name": "Int", "config": {"name": "units_19", "default": null, "conditions": [], "min_value": 5, "max_value": 100, "step": 5, "sampling": "linear"}}, {"class_name": "Choice", "config": {"name": "dp_rate_20", "default": 0.25, "conditions": [], "values": [0.25, 0.5, 0.75], "ordered": true}}, {"class_name": "Int", "config": {"name": "units_20", "default": null, "conditions": [], "min_value": 5, "max_value": 100, "step": 5, "sampling": "linear"}}, {"class_name": "Choice", "config": {"name": "dp_rate_21", "default": 0.25, "conditions": [], "values": [0.25, 0.5, 0.75], "ordered": true}}, {"class_name": "Int", "config": {"name": "units_21", "default": null, "conditions": [], "min_value": 5, "max_value": 100, "step": 5, "sampling": "linear"}}, {"class_name": "Choice", "config": {"name": "dp_rate_22", "default": 0.25, "conditions": [], "values": [0.25, 0.5, 0.75], "ordered": true}}, {"class_name": "Int", "config": {"name": "units_22", "default": null, "conditions": [], "min_value": 5, "max_value": 100, "step": 5, "sampling": "linear"}}, {"class_name": "Choice", "config": {"name": "dp_rate_23", "default": 0.25, "conditions": [], "values": [0.25, 0.5, 0.75], "ordered": true}}, {"class_name": "Int", "config": {"name": "units_23", "default": null, "conditions": [], "min_value": 5, "max_value": 100, "step": 5, "sampling": "linear"}}, {"class_name": "Choice", "config": {"name": "dp_rate_24", "default": 0.25, "conditions": [], "values": [0.25, 0.5, 0.75], "ordered": true}}, {"class_name": "Int", "config": {"name": "units_24", "default": null, "conditions": [], "min_value": 5, "max_value": 100, "step": 5, "sampling": "linear"}}, {"class_name": "Choice", "config": {"name": "dp_rate_25", "default": 0.25, "conditions": [], "values": [0.25, 0.5, 0.75], "ordered": true}}, {"class_name": "Int", "config": {"name": "units_25", "default": null, "conditions": [], "min_value": 5, "max_value": 100, "step": 5, "sampling": "linear"}}, {"class_name": "Choice", "config": {"name": "dp_rate_26", "default": 0.25, "conditions": [], "values": [0.25, 0.5, 0.75], "ordered": true}}, {"class_name": "Int", "config": {"name": "units_26", "default": null, "conditions": [], "min_value": 5, "max_value": 100, "step": 5, "sampling": "linear"}}, {"class_name": "Choice", "config": {"name": "dp_rate_27", "default": 0.25, "conditions": [], "values": [0.25, 0.5, 0.75], "ordered": true}}, {"class_name": "Int", "config": {"name": "units_27", "default": null, "conditions": [], "min_value": 5, "max_value": 100, "step": 5, "sampling": "linear"}}, {"class_name": "Choice", "config": {"name": "dp_rate_28", "default": 0.25, "conditions": [], "values": [0.25, 0.5, 0.75], "ordered": true}}, {"class_name": "Int", "config": {"name": "units_28", "default": null, "conditions": [], "min_value": 5, "max_value": 100, "step": 5, "sampling": "linear"}}, {"class_name": "Choice", "config": {"name": "dp_rate_29", "default": 0.25, "conditions": [], "values": [0.25, 0.5, 0.75], "ordered": true}}, {"class_name": "Int", "config": {"name": "units_29", "default": null, "conditions": [], "min_value": 5, "max_value": 100, "step": 5, "sampling": "linear"}}], "values": {"learning_rate": 0.001, "layers_units_x": 42, "layers_": 12, "dp_rate_0": 0.5, "units_0": 40, "dp_rate_1": 0.5, "units_1": 65, "dp_rate_2": 0.25, "units_2": 20, "dp_rate_3": 0.5, "units_3": 30, "dp_rate_4": 0.25, "units_4": 80, "dp_rate_5": 0.75, "units_5": 20, "dp_rate_6": 0.25, "units_6": 95, "dp_rate_7": 0.25, "units_7": 50, "dp_rate_8": 0.25, "units_8": 20, "dp_rate_9": 0.5, "units_9": 25, "dp_rate_10": 0.25, "units_10": 55, "dp_rate_11": 0.75, "units_11": 35, "dp_rate_12": 0.25, "units_12": 40, "dp_rate_13": 0.75, "units_13": 30, "dp_rate_14": 0.5, "units_14": 95, "dp_rate_15": 0.5, "units_15": 75, "dp_rate_16": 0.5, "units_16": 90, "dp_rate_17": 0.5, "units_17": 50, "dp_rate_18": 0.25, "units_18": 70, "dp_rate_19": 0.25, "units_19": 80, "dp_rate_20": 0.75, "units_20": 70, "dp_rate_21": 0.25, "units_21": 70, "dp_rate_22": 0.5, "units_22": 95, "dp_rate_23": 0.25, "units_23": 85, "dp_rate_24": 0.75, "units_24": 5, "dp_rate_25": 0.75, "units_25": 75, "dp_rate_26": 0.25, "units_26": 100, "dp_rate_27": 0.75, "units_27": 80, "dp_rate_28": 0.25, "units_28": 60, "dp_rate_29": 0.5, "units_29": 60}}, "metrics": {"metrics": {"accuracy": {"direction": "max", "observations": [{"value": [0.8629541993141174], "step": 5}]}, "loss": {"direction": "min", "observations": [{"value": [0.49178922176361084], "step": 5}]}, "val_accuracy": {"direction": "max", "observations": [{"value": [0.8672986030578613], "step": 5}]}, "val_loss": {"direction": "min", "observations": [{"value": [0.4654403626918793], "step": 5}]}}}, "score": 0.4654403626918793, "best_step": 5, "status": "COMPLETED", "message": null}